tmg_hmc/__init__.py
tmg_hmc/utils.py
tmg_hmc/compiled.cpython-313-x86_64-linux-gnu.so
tmg_hmc/constraints.py
tmg_hmc/quad_solns.h
tmg_hmc/quad_solns.cpp
tmg_hmc/quad_solns.py
tmg_hmc/sampler.py
tmg_hmc-1.0.0.dist-info/RECORD
tmg_hmc-1.0.0.dist-info/WHEEL
tmg_hmc-1.0.0.dist-info/METADATA
tmg_hmc-1.0.0.dist-info/top_level.txt
tmg_hmc-1.0.0.dist-info/licenses/LICENSE
