Metadata-Version: 2.4
Name: tmg_hmc
Version: 1.0.0
Summary: This package implements exact HMC sampling for truncated multivariate gaussians with quadratic constraints
Author-email: "Erik A. Bensen" <ebensen@andrew.cmu.edu>
License-Expression: MIT
Project-URL: Homepage, https://github.com/erik-a-bensen/tmg_hmc
Project-URL: Repository, https://github.com/erik-a-bensen/tmg_hmc
Project-URL: Issues, https://github.com/erik-a-bensen/tmg_hmc/issues
Classifier: Programming Language :: Python :: 3
Classifier: Operating System :: OS Independent
Requires-Python: >=3.10
License-File: LICENSE
Requires-Dist: numpy
Requires-Dist: scipy
Provides-Extra: gpu
Requires-Dist: torch>=2.0.0; extra == "gpu"
Provides-Extra: test
Requires-Dist: pytest>=7.0; extra == "test"
Requires-Dist: pytest-cov; extra == "test"
Requires-Dist: hypothesis>=6.100; extra == "test"
Provides-Extra: all
Requires-Dist: tmg_hmc[gpu,test]; extra == "all"
Dynamic: license-file
